research/AIImageDetector.ipynb
research/__init__.py
research/utils/__init__.py
research/utils/config.py
research/utils/dataset.py
research/utils/grad_cam.py
research/utils/model.py
research/utils/trainer.py
ai_image_detector_research-0.2.0.dist-info/METADATA
ai_image_detector_research-0.2.0.dist-info/WHEEL
ai_image_detector_research-0.2.0.dist-info/entry_points.txt
ai_image_detector_research-0.2.0.dist-info/RECORD
