Metadata-Version: 2.3
Name: ai-image-detector-research
Version: 0.2.0
Summary: 
Author: ycalk
Author-email: alosev752@gmail.com
Requires-Python: >=3.11
Classifier: Programming Language :: Python :: 3
Classifier: Programming Language :: Python :: 3.11
Classifier: Programming Language :: Python :: 3.12
Classifier: Programming Language :: Python :: 3.13
Requires-Dist: ipywidgets (>=8.1.7,<9.0.0)
Requires-Dist: kagglehub (>=0.3.12,<0.4.0)
Requires-Dist: matplotlib (>=3.10.3,<4.0.0)
Requires-Dist: opencv-python (>=4.12.0.88,<5.0.0.0)
Requires-Dist: pandas (>=2.3.1,<3.0.0)
Requires-Dist: python-dotenv (>=1.1.1,<2.0.0)
Requires-Dist: scikit-learn (>=1.7.0,<2.0.0)
Requires-Dist: seaborn (>=0.13.2,<0.14.0)
Requires-Dist: torch (>=2.7.1,<3.0.0)
Requires-Dist: torchaudio (>=2.7.1,<3.0.0)
Requires-Dist: torchvision (>=0.22.1,<0.23.0)
Requires-Dist: tqdm (>=4.67.1,<5.0.0)
